maillogger/__init__.py
maillogger/cli.py
maillogger/exceptions.py
maillogger/file/__init__.py
maillogger/file/base.py
maillogger/file/filetype.py
maillogger/file/loader.py
maillogger/file/writer.py
maillogger/main.py
maillogger/parser.py
maillogger-0.2.0.dist-info/entry_points.txt
maillogger-0.2.0.dist-info/LICENSE
maillogger-0.2.0.dist-info/WHEEL
maillogger-0.2.0.dist-info/METADATA
maillogger-0.2.0.dist-info/RECORD
