Metadata-Version: 2.1
Name: maillogger
Version: 0.2.0
Summary: Analysis tool for Postfix log in /var/log/maillog
Home-page: https://github.com/homoluctus/maillogger
License: MIT
Keywords: postfix,maillog
Author: homoluctus
Author-email: w.slife18sy@gmail.com
Requires-Python: >=3.7,<4.0
Classifier: License :: OSI Approved :: MIT License
Classifier: Programming Language :: Python :: 3
Classifier: Programming Language :: Python :: 3.7
Classifier: Programming Language :: Python :: 3.8
Project-URL: Repository, https://github.com/homoluctus/maillogger
